setup.py
distributions/Binomialdistribution.py
distributions/Gaussiandistribution.py
distributions/Generaldistribution.py
distributions/__init__.py
normalbinomialsampledistributions.egg-info/PKG-INFO
normalbinomialsampledistributions.egg-info/SOURCES.txt
normalbinomialsampledistributions.egg-info/dependency_links.txt
normalbinomialsampledistributions.egg-info/not-zip-safe
normalbinomialsampledistributions.egg-info/top_level.txt