Metadata-Version: 1.0
Name: normalbinomialsampledistributions
Version: 0.1
Summary: Sample - Normal and Binomial distributions
Home-page: UNKNOWN
Author: Guillermo Ampie
Author-email: ga.ampie@gmail.com
License: UNKNOWN
Platform: UNKNOWN
